README.md
setup.py
hashmap_data_validator.egg-info/PKG-INFO
hashmap_data_validator.egg-info/SOURCES.txt
hashmap_data_validator.egg-info/dependency_links.txt
hashmap_data_validator.egg-info/entry_points.txt
hashmap_data_validator.egg-info/requires.txt
hashmap_data_validator.egg-info/top_level.txt
hdv/__init__.py
hdv/cli_validator.py
hdv/validator.py
hdv/configurations/default_hdv_config.yml
hdv/configurations/default_hdv_profiles.yml
hdv/dao/__init__.py
hdv/dao/dao.py
hdv/dao/db_dao.py
hdv/dao/db_snowflake.py
hdv/dao/oracle.py
hdv/resources/__init__.py
hdv/resources/jdbc_resource.py
hdv/resources/oracle_rdbms_resource.py
hdv/resources/rdbms_resource.py
hdv/resources/resource.py
hdv/resources/snowflake_rdbms_resource.py
hdv/tests/__init__.py
hdv/tests/dao/__init__.py
hdv/tests/dao/test_oracle.py
hdv/tests/dao/test_snowflake.py
hdv/tests/utils/__init__.py
hdv/tests/utils/test_project_config.py
hdv/tests/validator/__init__.py
hdv/tests/validator/test_validator.py
hdv/utils/__init__.py
hdv/utils/parse_config.py
hdv/utils/project_config.py