Metadata-Version: 2.1
Name: hashmap-data-validator
Version: 0.1.0.0
Summary: A Python Package designed to validate data sources and sinks
Home-page: https://gitlab.com/hashmapinc/ctso/accelerators/data-engineering/hashmap_data_suite/hashmap-data-validator
Author: Hashmap, Inc
Author-email: accelerators@hashmapinc.com
License: UNKNOWN
Platform: UNKNOWN
Classifier: Programming Language :: Python :: 3
Classifier: License :: OSI Approved :: Apache Software License
Classifier: Operating System :: OS Independent
Classifier: Development Status :: 3 - Alpha
Requires-Python: >=3.7
